LICENSE
MANIFEST.in
README.md
setup.py
checklist/__init__.py
checklist/abstract_test.py
checklist/editor.py
checklist/expect.py
checklist/multilingual.py
checklist/perturb.py
checklist/pred_wrapper.py
checklist/run_commercial.py
checklist/test_suite.py
checklist/test_types.py
checklist/text_generation.py
checklist.egg-info/PKG-INFO
checklist.egg-info/SOURCES.txt
checklist.egg-info/dependency_links.txt
checklist.egg-info/not-zip-safe
checklist.egg-info/requires.txt
checklist.egg-info/top_level.txt
checklist/data/names.json
checklist/data/wikidata.pkl
checklist/data/lexicons/basic.json
checklist/viewer/__init__.py
checklist/viewer/fake_data.py
checklist/viewer/suite_summarizer.py
checklist/viewer/template_editor.py
checklist/viewer/test_summarizer.py
checklist/viewer/viewer.py
checklist/viewer/static/__init__.py
checklist/viewer/static/bundle.js
checklist/viewer/static/bundle.js.map
checklist/viewer/static/custom.js
checklist/viewer/static/extension.js
checklist/viewer/static/index.js
checklist/viewer/static/index.js.map