Metadata-Version: 1.0
Name: checklist
Version: 0.0.4
Summary: Beyond Accuracy: Behavioral Testing of NLP Models with CheckList
Home-page: http://github.com/marcotcr/checklist
Author: Marco Tulio Ribeiro
Author-email: marcotcr@gmail.com
License: MIT
Platform: UNKNOWN
